pfp_lgbt/__init__.py
pfp_lgbt/client.py
pfp_lgbt/error.py
pfp_lgbt/handlers.py
pfp_lgbt/models.py
pfp_lgbt/throttle.py
pfp_lgbt/util.py
pfp_lgbt-1.0.2.dist-info/LICENSE
pfp_lgbt-1.0.2.dist-info/METADATA
pfp_lgbt-1.0.2.dist-info/WHEEL
pfp_lgbt-1.0.2.dist-info/top_level.txt
pfp_lgbt-1.0.2.dist-info/RECORD
