Metadata-Version: 2.1
Name: pfp-lgbt
Version: 1.0.2
Summary: Python API Wrapper for https://pfp.lgbt/
Home-page: https://github.com/Weilbyte/pfp_lgbt.py
Author: Weilbyte
License: UNKNOWN
Platform: UNKNOWN
Classifier: Programming Language :: Python :: 3.6
Classifier: Programming Language :: Python :: 3.7
Classifier: Programming Language :: Python :: 3.8
Classifier: License :: OSI Approved :: MIT License
Classifier: Intended Audience :: Developers
Classifier: Natural Language :: English
Classifier: Operating System :: OS Independent
Classifier: Topic :: Software Development :: Libraries :: Python Modules
Requires-Python: >=3.6
Requires-Dist: aiohttp
